degender_pronoun
